LICENSE
README.md
pyproject.toml
setup.py
src/binx_og_image_generator/__init__.py
src/binx_og_image_generator/__main__.py
src/binx_og_image_generator/generator.py
src/binx_og_image_generator/gravatar.py
src/binx_og_image_generator/logger.py
src/binx_og_image_generator.egg-info/PKG-INFO
src/binx_og_image_generator.egg-info/SOURCES.txt
src/binx_og_image_generator.egg-info/dependency_links.txt
src/binx_og_image_generator.egg-info/entry_points.txt
src/binx_og_image_generator.egg-info/not-zip-safe
src/binx_og_image_generator.egg-info/requires.txt
src/binx_og_image_generator.egg-info/top_level.txt
src/binx_og_image_generator/fonts/CONTRIBUTING.txt
src/binx_og_image_generator/fonts/FONTLOG.txt
src/binx_og_image_generator/fonts/LICENCE-FAQ.txt
src/binx_og_image_generator/fonts/LICENCE.txt
src/binx_og_image_generator/fonts/README.txt
src/binx_og_image_generator/fonts/TRADEMARKS.txt
src/binx_og_image_generator/fonts/Ubuntu-B.ttf
src/binx_og_image_generator/fonts/Ubuntu-BI.ttf
src/binx_og_image_generator/fonts/Ubuntu-C.ttf
src/binx_og_image_generator/fonts/Ubuntu-L.ttf
src/binx_og_image_generator/fonts/Ubuntu-LI.ttf
src/binx_og_image_generator/fonts/Ubuntu-M.ttf
src/binx_og_image_generator/fonts/Ubuntu-MI.ttf
src/binx_og_image_generator/fonts/Ubuntu-R.ttf
src/binx_og_image_generator/fonts/Ubuntu-RI.ttf
src/binx_og_image_generator/fonts/UbuntuMono-B.ttf
src/binx_og_image_generator/fonts/UbuntuMono-BI.ttf
src/binx_og_image_generator/fonts/UbuntuMono-R.ttf
src/binx_og_image_generator/fonts/UbuntuMono-RI.ttf
src/binx_og_image_generator/fonts/copyright.txt
src/binx_og_image_generator/fonts/encodings.dir
src/binx_og_image_generator/fonts/fonts.dir
src/binx_og_image_generator/fonts/fonts.list
src/binx_og_image_generator/fonts/fonts.scale
src/binx_og_image_generator/fonts/proximanova-black-italic.ttf
src/binx_og_image_generator/fonts/proximanova-black.ttf
src/binx_og_image_generator/fonts/proximanova-bold-italic.ttf
src/binx_og_image_generator/fonts/proximanova-bold.ttf
src/binx_og_image_generator/fonts/proximanova-extrabold-italic.ttf
src/binx_og_image_generator/fonts/proximanova-extrabold.ttf
src/binx_og_image_generator/fonts/proximanova-light-italic.ttf
src/binx_og_image_generator/fonts/proximanova-light.ttf
src/binx_og_image_generator/fonts/proximanova-medium.ttf
src/binx_og_image_generator/fonts/proximanova-regular-italic.ttf
