Metadata-Version: 2.1
Name: binx-og-image-generator
Version: 1.2.0
Summary: generates og image for xebia.com and binx.io blog
Home-page: https://github.com/binxio/og-image-generator
Author: Mark van Holsteijn
Author-email: mark@binx.io
License: restricted
Platform: any
Classifier: Development Status :: 4 - Beta
Classifier: Environment :: Console
Classifier: Intended Audience :: Developers
Classifier: Operating System :: POSIX
Classifier: Operating System :: MacOS
Classifier: Operating System :: Unix
Classifier: Operating System :: Microsoft :: Windows
Classifier: Programming Language :: Python
Classifier: Programming Language :: Python :: 3
Classifier: Topic :: Software Development :: Libraries :: Python Modules
License-File: LICENSE
